Metadata-Version: 1.1
Name: keras2pmml
Version: 0.1.0
Summary: Simple exporter of Keras models into PMML
Home-page: https://github.com/vaclavcadek/keras2pmml
Author: Václav Čadek
Author-email: vaclavcadek@gmail.com
License: MIT
Platform: UNKNOWN
Classifier: Intended Audience :: Science/Research
Classifier: Intended Audience :: Developers
Classifier: Development Status :: 3 - Alpha
Classifier: Operating System :: OS Independent
Classifier: Programming Language :: Python
Classifier: Programming Language :: Python :: 3 :: Only
Classifier: Topic :: Software Development :: Libraries
Classifier: Topic :: Software Development :: Libraries :: Python Modules
